{
  "generatedAt": "2026-04-19T00:27:28+09:00",
  "topN": 20,
  "creators": [
    {
      "anchorId": "6515019362902392833",
      "nickname": "nicamop",
      "username": "nicamoq",
      "avatar": "https://p16-common-sign.tiktokcdn.com/tos-alisg-avt-0068/8984f98cff772613ec09223dfaf8677b~tplv-tiktokx-cropcenter:100:100.jpeg?dr=14579&refresh_token=3fe6e1dd&x-expires=1776697200&x-signature=wWd%2FEySkP%2Bkqaz1pt9Wq1q94xMU%3D&t=4d5b0474&ps=13740610&shp=a5d48078&shcp=d2876c74&idc=my",
      "isLive": false,
      "totalDiamonds": 19033600,
      "lastMonthDiamonds": 7012944,
      "pkDiamondsMtd": 7746189,
      "broadcastDays": 7,
      "broadcastDurationHours": 29.98638888888889,
      "contributionBonusUSD": 0,
      "lastMonthContributionBonusUSD": 0,
      "group": "",
      "manager": "yuki.sazanami",
      "managerRaw": "",
      "agent": "yuki.sazanami",
      "source": "アルファ",
      "isCurrentAgency": true,
      "rank": 1,
      "displayRank": 1
    },
    {
      "anchorId": "6901280326077744130",
      "nickname": "Naru👼🩵",
      "username": "naru_golf",
      "avatar": "https://p16-common-sign.tiktokcdn.com/tos-alisg-avt-0068/8d8b3ce6252e2bff126c0927e587c4f4~tplv-tiktokx-cropcenter:100:100.jpeg?dr=14579&refresh_token=1ed42f0a&x-expires=1776610800&x-signature=DKvy2UpREZTVeSk8L5Ot9CItn0U%3D&t=4d5b0474&ps=13740610&shp=d2876c74&shcp=9b759fb9&idc=my",
      "isLive": true,
      "totalDiamonds": 6882066,
      "lastMonthDiamonds": 3600230,
      "pkDiamondsMtd": 4530267,
      "broadcastDays": 16,
      "broadcastDurationHours": 97.32444444444444,
      "contributionBonusUSD": 688.2066,
      "lastMonthContributionBonusUSD": 720.046,
      "group": "",
      "manager": "yuki.sazanami",
      "managerRaw": "",
      "agent": "yuki.sazanami",
      "source": "アルファ",
      "isCurrentAgency": true,
      "rank": 2,
      "displayRank": 2
    },
    {
      "anchorId": "7053170757614945282",
      "nickname": "神社あゆ",
      "username": "a.jinja",
      "avatar": "https://p16-common-sign.tiktokcdn.com/tos-alisg-avt-0068/bd9b616439304786087e80c2c6e23818~tplv-tiktokx-cropcenter:100:100.jpeg?dr=14579&refresh_token=41918529&x-expires=1776610800&x-signature=DhoTft0R8%2FRqFi3BVkYAsHyzQrc%3D&t=4d5b0474&ps=13740610&shp=d2876c74&shcp=9b759fb9&idc=my",
      "isLive": false,
      "totalDiamonds": 1988284,
      "lastMonthDiamonds": 777760,
      "pkDiamondsMtd": 1244280,
      "broadcastDays": 16,
      "broadcastDurationHours": 96.43638888888889,
      "contributionBonusUSD": 198.8284,
      "lastMonthContributionBonusUSD": 77.776,
      "group": "HIKE",
      "manager": "haruno.tsutsumi.bcode",
      "managerRaw": "m.kagami",
      "agent": "haruno.tsutsumi.bcode",
      "source": "アルファ",
      "isCurrentAgency": true,
      "rank": 3,
      "displayRank": 3
    },
    {
      "anchorId": "6991708846167262210",
      "nickname": "タン塩。🧂🐈‍⬛",
      "username": "tanchan._.m",
      "avatar": "https://p16-common-sign.tiktokcdn.com/tos-alisg-avt-0068/8c4a4fc23328ca3898a76962d4479257~tplv-tiktokx-cropcenter:100:100.jpeg?dr=14579&refresh_token=2b46170c&x-expires=1776610800&x-signature=cNT3xkeWB0Leyy0ldFAcJI8%2FysY%3D&t=4d5b0474&ps=13740610&shp=d2876c74&shcp=9b759fb9&idc=my",
      "isLive": false,
      "totalDiamonds": 1915763,
      "lastMonthDiamonds": 1321465,
      "pkDiamondsMtd": 1210677,
      "broadcastDays": 17,
      "broadcastDurationHours": 142.74388888888888,
      "contributionBonusUSD": 191.5763,
      "lastMonthContributionBonusUSD": 264.293,
      "group": "パパパ",
      "manager": "tomoki.imanishi.bcode",
      "managerRaw": "tomoki.imanishi.bcode",
      "agent": "tomoki.imanishi.bcode",
      "source": "アルファ",
      "isCurrentAgency": true,
      "rank": 4,
      "displayRank": 4
    },
    {
      "anchorId": "7324749324759827464",
      "nickname": "ちゃんゆ~🌻🫧",
      "username": "54321i.yr",
      "avatar": "https://p16-sign-sg.tiktokcdn.com/tos-alisg-avt-0068/b32e1eb08d8ae4b23caac81e349b76a6~tplv-tiktokx-cropcenter:100:100.jpeg?dr=14579&refresh_token=1611701d&x-expires=1776697200&x-signature=s24tTV1VN8FPo0e4nvCDavF5U3M%3D&t=4d5b0474&ps=13740610&shp=a5d48078&shcp=d2876c74&idc=my",
      "isLive": false,
      "totalDiamonds": 1726412,
      "lastMonthDiamonds": 1279724,
      "pkDiamondsMtd": 1337658,
      "broadcastDays": 17,
      "broadcastDurationHours": 111.01138888888889,
      "contributionBonusUSD": 172.6412,
      "lastMonthContributionBonusUSD": 127.9724,
      "group": "パパパ",
      "manager": "tomoki.imanishi.bcode",
      "managerRaw": "tomoki.imanishi.bcode",
      "agent": "tomoki.imanishi.bcode",
      "source": "アルファ",
      "isCurrentAgency": true,
      "rank": 5,
      "displayRank": 5
    },
    {
      "anchorId": "7363947924744078354",
      "nickname": "さくらもち🌸🌊",
      "username": "sakurabyori_03",
      "avatar": "https://p19-common-sign.tiktokcdn.com/tos-alisg-avt-0068/e773e2917b0f7e2b020d11204897ddd4~tplv-tiktokx-cropcenter:100:100.jpeg?dr=14579&refresh_token=f1b5c342&x-expires=1776610800&x-signature=HJojz8cDKjGkmalcJaMhWzSMnWc%3D&t=4d5b0474&ps=13740610&shp=d2876c74&shcp=9b759fb9&idc=my",
      "isLive": true,
      "totalDiamonds": 1680452,
      "lastMonthDiamonds": 2989554,
      "pkDiamondsMtd": 654710,
      "broadcastDays": 14,
      "broadcastDurationHours": 44.40277777777778,
      "contributionBonusUSD": 84.0226,
      "lastMonthContributionBonusUSD": 149.4777,
      "group": "パパパ",
      "manager": "tomoki.imanishi.bcode",
      "managerRaw": "tomoki.imanishi.bcode",
      "agent": "tomoki.imanishi.bcode",
      "source": "アルファ",
      "isCurrentAgency": true,
      "rank": 6,
      "displayRank": 6
    },
    {
      "anchorId": "7553252436724597781",
      "nickname": "akka🦋💙",
      "username": "akka1230_",
      "avatar": "https://p16-common-sign.tiktokcdn.com/tos-alisg-avt-0068/b3948957217736b80904d8e658a4f63e~tplv-tiktokx-cropcenter:100:100.jpeg?dr=14579&refresh_token=0dc01b7b&x-expires=1776610800&x-signature=kkbmsAOV0j%2BjuXKg12wkz7fx70I%3D&t=4d5b0474&ps=13740610&shp=d2876c74&shcp=9b759fb9&idc=my",
      "isLive": false,
      "totalDiamonds": 1667261,
      "lastMonthDiamonds": 2467154,
      "pkDiamondsMtd": 1384924,
      "broadcastDays": 14,
      "broadcastDurationHours": 29.628333333333334,
      "contributionBonusUSD": 83.363,
      "lastMonthContributionBonusUSD": 2097.0809,
      "group": "パパパ",
      "manager": "tomoki.imanishi.bcode",
      "managerRaw": "tomoki.imanishi.bcode",
      "agent": "tomoki.imanishi.bcode",
      "source": "アルファ",
      "isCurrentAgency": true,
      "rank": 7,
      "displayRank": 7
    },
    {
      "anchorId": "7283769314519270402",
      "nickname": "🌞ヒカリ🌞🌊🧜🏽‍♀️💙",
      "username": "0843hikari",
      "avatar": "https://p16-common-sign.tiktokcdn.com/tos-alisg-avt-0068/73e27b27c043939f87bc5b5bd0be8df2~tplv-tiktokx-cropcenter:100:100.jpeg?dr=14579&refresh_token=a8a87025&x-expires=1776697200&x-signature=iLZTUfTOeMty3EDWq3ehjQVfPU8%3D&t=4d5b0474&ps=13740610&shp=a5d48078&shcp=d2876c74&idc=my",
      "isLive": false,
      "totalDiamonds": 1578337,
      "lastMonthDiamonds": 700713,
      "pkDiamondsMtd": 1505947,
      "broadcastDays": 16,
      "broadcastDurationHours": 85.24222222222222,
      "contributionBonusUSD": 157.8337,
      "lastMonthContributionBonusUSD": 35.0356,
      "group": "",
      "manager": "yuki.sazanami",
      "managerRaw": "",
      "agent": "yuki.sazanami",
      "source": "アルファ",
      "isCurrentAgency": true,
      "rank": 8,
      "displayRank": 8
    },
    {
      "anchorId": "7037318688395854849",
      "nickname": "その後の凛🐿️💉",
      "username": "tktwpwtm",
      "avatar": "https://p19-common-sign.tiktokcdn.com/tos-alisg-avt-0068/319fd67311c5790af11b2971aeaa1df7~tplv-tiktokx-cropcenter:100:100.jpeg?dr=14579&refresh_token=47c2258f&x-expires=1776697200&x-signature=tfkIF5Zx%2BadccvK3Jdj7Yn0pHw8%3D&t=4d5b0474&ps=13740610&shp=a5d48078&shcp=d2876c74&idc=my",
      "isLive": true,
      "totalDiamonds": 1505863,
      "lastMonthDiamonds": 1164661,
      "pkDiamondsMtd": 943290,
      "broadcastDays": 15,
      "broadcastDurationHours": 56.00833333333333,
      "contributionBonusUSD": 150.5863,
      "lastMonthContributionBonusUSD": 116.4661,
      "group": "アルファ",
      "manager": "katsuaki.takizawa.grove",
      "managerRaw": "katsuaki.takizawa.grove",
      "agent": "katsuaki.takizawa.grove",
      "source": "ユリシス",
      "isCurrentAgency": true,
      "rank": 9,
      "displayRank": 9
    },
    {
      "anchorId": "7542918611334546439",
      "nickname": "おりひめ🎋👑ｷﾞﾌﾄｽﾀｰ🌟🔥",
      "username": "orihinenanoda",
      "avatar": "https://p16-common-sign.tiktokcdn.com/tos-alisg-avt-0068/e7a6e0874ecc812f65d833929a42b8c2~tplv-tiktokx-cropcenter:100:100.jpeg?dr=14579&refresh_token=2187486a&x-expires=1776610800&x-signature=xH1w4LwVnqqWnWwZlSmyOe2muow%3D&t=4d5b0474&ps=13740610&shp=d2876c74&shcp=9b759fb9&idc=my",
      "isLive": false,
      "totalDiamonds": 1355790,
      "lastMonthDiamonds": 295523,
      "pkDiamondsMtd": 617126,
      "broadcastDays": 18,
      "broadcastDurationHours": 91.8561111111111,
      "contributionBonusUSD": 271.158,
      "lastMonthContributionBonusUSD": 29.5523,
      "group": "HIKE",
      "manager": "haruno.tsutsumi.bcode",
      "managerRaw": "m.kagami",
      "agent": "haruno.tsutsumi.bcode",
      "source": "アルファ",
      "isCurrentAgency": true,
      "rank": 11,
      "displayRank": 10
    },
    {
      "anchorId": "7065935864510383106",
      "nickname": "劇団りなりん🍎🧞‍♂️はずっと思春期(武田莉奈)",
      "username": "rinatakeda_0113",
      "avatar": "https://p77-sign-sg.tiktokcdn.com/tos-alisg-avt-0068/e813e4daa83e5c5242795e642afee8a0~tplv-tiktokx-cropcenter:100:100.jpeg?dr=14579&refresh_token=97cd373a&x-expires=1776697200&x-signature=qzYIZvvysnIAGQgNp3MGfJ0qB6o%3D&t=4d5b0474&ps=13740610&shp=a5d48078&shcp=d2876c74&idc=my",
      "isLive": false,
      "totalDiamonds": 1270582,
      "lastMonthDiamonds": 2686856,
      "pkDiamondsMtd": 1084849,
      "broadcastDays": 10,
      "broadcastDurationHours": 45.51638888888889,
      "contributionBonusUSD": 63.5291,
      "lastMonthContributionBonusUSD": 268.6856,
      "group": "",
      "manager": "yuki.sazanami",
      "managerRaw": "",
      "agent": "yuki.sazanami",
      "source": "アルファ",
      "isCurrentAgency": true,
      "rank": 14,
      "displayRank": 11
    },
    {
      "anchorId": "6815997523792282625",
      "nickname": "板野成美 なるっぴ【RoLuANGEL🩷🪽】",
      "username": "naru0821",
      "avatar": "https://p16-common-sign.tiktokcdn.com/tos-alisg-avt-0068/00148074d3a2c171c5b936e4860acd0f~tplv-tiktokx-cropcenter:100:100.jpeg?dr=14579&refresh_token=4fb4d334&x-expires=1776610800&x-signature=P0RtUMmo5bC%2BePYoZ0ocpOlfUa8%3D&t=4d5b0474&ps=13740610&shp=d2876c74&shcp=9b759fb9&idc=my",
      "isLive": false,
      "totalDiamonds": 1217519,
      "lastMonthDiamonds": 360,
      "pkDiamondsMtd": 11352,
      "broadcastDays": 13,
      "broadcastDurationHours": 45.03388888888889,
      "contributionBonusUSD": 60.8759,
      "lastMonthContributionBonusUSD": 0,
      "group": "",
      "manager": "yuki.sazanami",
      "managerRaw": "",
      "agent": "yuki.sazanami",
      "source": "アルファ",
      "isCurrentAgency": true,
      "rank": 15,
      "displayRank": 12
    },
    {
      "anchorId": "7329761192728478727",
      "nickname": "きゃのん🐉🟠⭐️",
      "username": "canon.kyanon35",
      "avatar": "https://p16-common-sign.tiktokcdn.com/tos-alisg-avt-0068/a64f14134bb7efaa0f9319ec5d2b6e56~tplv-tiktokx-cropcenter:100:100.jpeg?dr=14579&refresh_token=47e47343&x-expires=1776610800&x-signature=pXA1q84Kuidxq28Qb%2F6NqrDm7gU%3D&t=4d5b0474&ps=13740610&shp=d2876c74&shcp=9b759fb9&idc=my",
      "isLive": false,
      "totalDiamonds": 1138260,
      "lastMonthDiamonds": 1048947,
      "pkDiamondsMtd": 394376,
      "broadcastDays": 16,
      "broadcastDurationHours": 95.48694444444445,
      "contributionBonusUSD": 113.826,
      "lastMonthContributionBonusUSD": 52.4473,
      "group": "",
      "manager": "yuki.sazanami",
      "managerRaw": "",
      "agent": "yuki.sazanami",
      "source": "アルファ",
      "isCurrentAgency": true,
      "rank": 17,
      "displayRank": 13
    },
    {
      "anchorId": "6550463899762114562",
      "nickname": "ゆっち🐶🍃",
      "username": "cancororo_",
      "avatar": "https://p16-common-sign.tiktokcdn.com/tos-alisg-avt-0068/8787ccb12ee20246f6eba54876f0d180~tplv-tiktokx-cropcenter:100:100.jpeg?dr=14579&refresh_token=26ee7550&x-expires=1776697200&x-signature=4KauAsPguiJgyFJIrVvyuYth0Lg%3D&t=4d5b0474&ps=13740610&shp=a5d48078&shcp=d2876c74&idc=my",
      "isLive": true,
      "totalDiamonds": 1090846,
      "lastMonthDiamonds": 195260,
      "pkDiamondsMtd": 617391,
      "broadcastDays": 15,
      "broadcastDurationHours": 44.3775,
      "contributionBonusUSD": 54.5423,
      "lastMonthContributionBonusUSD": 0,
      "group": "パパパ",
      "manager": "tomoki.imanishi.bcode",
      "managerRaw": "tomoki.imanishi.bcode",
      "agent": "tomoki.imanishi.bcode",
      "source": "アルファ",
      "isCurrentAgency": true,
      "rank": 20,
      "displayRank": 14
    },
    {
      "anchorId": "6690474551555703810",
      "nickname": "ヒノカ˙˚ʚ( ´ᵕ`⸝⸝⸝ )ɞ˚˙",
      "username": "hinokal1",
      "avatar": "https://p16-common-sign.tiktokcdn.com/tos-alisg-avt-0068/585d68d4f8bfe4721c9225b7677c8b53~tplv-tiktokx-cropcenter:100:100.jpeg?dr=14579&refresh_token=e0d48745&x-expires=1776697200&x-signature=EsBKAJoGuLG89w912HSXH9GvzlY%3D&t=4d5b0474&ps=13740610&shp=a5d48078&shcp=d2876c74&idc=my",
      "isLive": true,
      "totalDiamonds": 1007411,
      "lastMonthDiamonds": 751762,
      "pkDiamondsMtd": 716960,
      "broadcastDays": 16,
      "broadcastDurationHours": 88.89277777777778,
      "contributionBonusUSD": 100.7411,
      "lastMonthContributionBonusUSD": 75.1762,
      "group": "パパパ",
      "manager": "tomoki.imanishi.bcode",
      "managerRaw": "tomoki.imanishi.bcode",
      "agent": "tomoki.imanishi.bcode",
      "source": "アルファ",
      "isCurrentAgency": true,
      "rank": 21,
      "displayRank": 15
    },
    {
      "anchorId": "7324645523116966920",
      "nickname": "おはな【RoLuANGEL🩷🪽】",
      "username": "ohana.chan39",
      "avatar": "https://p16-common-sign.tiktokcdn.com/tos-alisg-avt-0068/4d9e5ee82cccf3098427f741e29e0786~tplv-tiktokx-cropcenter:100:100.jpeg?dr=14579&refresh_token=896cc115&x-expires=1776697200&x-signature=6ZeqSXwpHD8E9o321MJj8epTTZE%3D&t=4d5b0474&ps=13740610&shp=a5d48078&shcp=d2876c74&idc=my",
      "isLive": false,
      "totalDiamonds": 987027,
      "lastMonthDiamonds": 130,
      "pkDiamondsMtd": 17819,
      "broadcastDays": 13,
      "broadcastDurationHours": 47.672777777777775,
      "contributionBonusUSD": 49.3513,
      "lastMonthContributionBonusUSD": 0,
      "group": "",
      "manager": "yuki.sazanami",
      "managerRaw": "",
      "agent": "yuki.sazanami",
      "source": "アルファ",
      "isCurrentAgency": true,
      "rank": 22,
      "displayRank": 16
    },
    {
      "anchorId": "7415854757162009608",
      "nickname": "かとう🍵",
      "username": "kato.1126",
      "avatar": "https://p16-common-sign.tiktokcdn.com/tos-alisg-avt-0068/f3622168fd3e245d7125cc2aaf33408c~tplv-tiktokx-cropcenter:100:100.jpeg?dr=14579&refresh_token=75a5fc06&x-expires=1776697200&x-signature=8p0V%2FH92jm7aeW5xB6sU5ijlCz8%3D&t=4d5b0474&ps=13740610&shp=a5d48078&shcp=d2876c74&idc=my",
      "isLive": false,
      "totalDiamonds": 961491,
      "lastMonthDiamonds": 1370130,
      "pkDiamondsMtd": 763315,
      "broadcastDays": 18,
      "broadcastDurationHours": 66.6425,
      "contributionBonusUSD": 96.1491,
      "lastMonthContributionBonusUSD": 137.013,
      "group": "SINCEED",
      "manager": "katsuaki.takizawa.bcode",
      "managerRaw": "katsuaki.takizawa.bcode",
      "agent": "katsuaki.takizawa.bcode",
      "source": "アルファ",
      "isCurrentAgency": true,
      "rank": 23,
      "displayRank": 17
    },
    {
      "anchorId": "6580975639502536705",
      "nickname": "みぃ🐇❄️",
      "username": "me1_sha",
      "avatar": "https://p16-common-sign.tiktokcdn.com/tos-alisg-avt-0068/37ce325b84f90fa6f8fd0dbedd2c65f5~tplv-tiktokx-cropcenter:100:100.jpeg?dr=14579&refresh_token=e9049ddb&x-expires=1776697200&x-signature=aiyaZ1siQU4%2FUzcC5kXH91ZqbJ8%3D&t=4d5b0474&ps=13740610&shp=a5d48078&shcp=d2876c74&idc=my",
      "isLive": false,
      "totalDiamonds": 949577,
      "lastMonthDiamonds": 369739,
      "pkDiamondsMtd": 162819,
      "broadcastDays": 17,
      "broadcastDurationHours": 78.71527777777777,
      "contributionBonusUSD": 94.9577,
      "lastMonthContributionBonusUSD": 36.9739,
      "group": "パパパ",
      "manager": "tomoki.imanishi.bcode",
      "managerRaw": "tomoki.imanishi.bcode",
      "agent": "tomoki.imanishi.bcode",
      "source": "アルファ",
      "isCurrentAgency": true,
      "rank": 24,
      "displayRank": 18
    },
    {
      "anchorId": "7254608079927968770",
      "nickname": "スナック🥃りったん🌷🌸",
      "username": "rittan0134",
      "avatar": "https://p16-common-sign.tiktokcdn.com/tos-alisg-avt-0068/d7e1a0192fc3e6f56f6a7296e0105b67~tplv-tiktokx-cropcenter:100:100.jpeg?dr=14579&refresh_token=0509e1ff&x-expires=1776697200&x-signature=tRo10tepHT29TE2N1nzRGyovez0%3D&t=4d5b0474&ps=13740610&shp=a5d48078&shcp=d2876c74&idc=my",
      "isLive": false,
      "totalDiamonds": 949064,
      "lastMonthDiamonds": 1019953,
      "pkDiamondsMtd": 923077,
      "broadcastDays": 15,
      "broadcastDurationHours": 83.09388888888888,
      "contributionBonusUSD": 94.9064,
      "lastMonthContributionBonusUSD": 101.9953,
      "group": "Bcode社内",
      "manager": "hiroki.tanaka.bcode",
      "managerRaw": "taishi.kobayashi",
      "agent": "hiroki.tanaka.bcode",
      "source": "アルファ",
      "isCurrentAgency": true,
      "rank": 25,
      "displayRank": 19
    },
    {
      "anchorId": "7537954860601558024",
      "nickname": "まるぱん🐶🌻🔴",
      "username": "marupan_nurse",
      "avatar": "https://p16-common-sign.tiktokcdn.com/tos-alisg-avt-0068/ba945550e2ea4ccbf0cbb8efe2e09ca5~tplv-tiktokx-cropcenter:100:100.jpeg?dr=14579&refresh_token=ef19eae5&x-expires=1776697200&x-signature=KSzimroi8CJA94HUenkmDyw4IKw%3D&t=4d5b0474&ps=13740610&shp=a5d48078&shcp=d2876c74&idc=my",
      "isLive": false,
      "totalDiamonds": 925406,
      "lastMonthDiamonds": 1210192,
      "pkDiamondsMtd": 561828,
      "broadcastDays": 18,
      "broadcastDurationHours": 85.64777777777778,
      "contributionBonusUSD": 185.0812,
      "lastMonthContributionBonusUSD": 242.0384,
      "group": "HIKE",
      "manager": "haruno.tsutsumi.bcode",
      "managerRaw": "m.kagami",
      "agent": "haruno.tsutsumi.bcode",
      "source": "アルファ",
      "isCurrentAgency": true,
      "rank": 26,
      "displayRank": 20
    }
  ]
}